{
  {
    "name":"DressForm",
    "height":"",
    "full_length_front":44.5,
    "shoulder_slope_front":46,
    "shoulder_length":12.5,
    "bust":105.5,
    "chest_width":35.5,
    "bust_point_from_shoulder":27.5,
    "bust_point_to_bust_point":20.5,
    "waist_front_to_dart":6.75,
    "diff_center_back_full_back":5,
    "center_length_back":38.5,
    "full_length_back":43.5,
    "shoulder_width_back":40,
    "shoulder_slope_back":43,
    "neck_back":20,
    "hip_length_front":22,
    "abdomen":51,
    "shoulder_to_wrist":"",
    "underarm_length":"",
    "shoulder_to_elbow":"",
    "upper_arm_width":"",
    "elbow_width":"",
    "wrist_width":"",
    "crotch_depth":"",
    "knee_depth":"",
    "base_hem_width":35,
    "waist":89,
    "hip":111,
    "bust_front":56.5,
    "bust_back":49,
    "body_width":110,
    "body_width_front":59,
    "body_width_back":51,
    "measurement_units":"cm",
    "center_length_front":35.5,
    "shoulder_width_front":41,
    "waist_front":48,
    "waist_back":41,
    "waist_back_to_dart":5.75,
    "back_width":33,
    "hip_length_side":20.5,
    "hip_length_back":22.5,
    "hip_front":52,
    "waist_to_floor_front":110,
    "hip_back":58,
    "thigh":"",
    "knee":"",
    "side_seam_length":18,
    "hand_width":"",
    "hip_to_floor":88
  }
}
